data_quality_summarizer/__init__.py
data_quality_summarizer/__main__.py
data_quality_summarizer/aggregator.py
data_quality_summarizer/constants.py
data_quality_summarizer/ingestion.py
data_quality_summarizer/rules.py
data_quality_summarizer/summarizer.py
data_quality_summarizer/ml/__init__.py
data_quality_summarizer/ml/ab_testing.py
data_quality_summarizer/ml/aggregator.py
data_quality_summarizer/ml/batch_predictor.py
data_quality_summarizer/ml/comprehensive_validator.py
data_quality_summarizer/ml/data_loader.py
data_quality_summarizer/ml/data_splitter.py
data_quality_summarizer/ml/data_validator.py
data_quality_summarizer/ml/evaluator.py
data_quality_summarizer/ml/feature_engineer.py
data_quality_summarizer/ml/feature_pipeline.py
data_quality_summarizer/ml/feature_utils.py
data_quality_summarizer/ml/hyperparameter_optimization.py
data_quality_summarizer/ml/model_trainer.py
data_quality_summarizer/ml/model_validator.py
data_quality_summarizer/ml/optimizer.py
data_quality_summarizer/ml/performance_monitor.py
data_quality_summarizer/ml/pipeline.py
data_quality_summarizer/ml/predictor.py
data_quality_summarizer/ml/production.py
data_quality_summarizer/ml/validator.py
data_quality_summarizer_7-0.1.1.dist-info/METADATA
data_quality_summarizer_7-0.1.1.dist-info/WHEEL
data_quality_summarizer_7-0.1.1.dist-info/top_level.txt
data_quality_summarizer_7-0.1.1.dist-info/RECORD
